{"EntityText":"#: E-000-2240426 Date: 12\/13\/2021 Stock: VS1179 RO: F3267226 PO:  (2021 VW VIRTUS 9BWDL5BZ1MP019919) Client: LUIS ENRIQUE","UTCTimestamp":"2022-03-28T04:28:03.503","InspectionId":"1BA2EBEA-F0EE-4CFF-8A9D-5144D6552A5C","InspectionNumber":"E-000-2240426","InspectionDate":"2021-12-13","InspectionType":{"Id":"04A19838-AEEC-4B12-BC41-77C52A166A0E","Name":"Hoja de Inspección - check in"},"Amount":0.00,"ApprovedAmount":0.00,"DiscountAmount":0.00000,"TaxAmount":0.00000,"FeesAmount":0.00000,"Employee":{"Id":"897AF737-C484-4D9C-9FEA-C21B99EABE11","Name":"HERTZ SAN50-01","ExternalID":null},"Client":{"Id":"5CB75F79-5116-423D-B30E-80F21B48FFA4","Name":"LUIS ENRIQUE","Address":"C TLALOC","Phone":"3336673614","ExternalID":null},"Vehicle":{"VIN":"9BWDL5BZ1MP019919","Year":2021,"Make":"VW","Model":"VIRTUS","PlateNo":"11-92-AVE","Vehicle":{"Color":null},"Mileage":23701,"PaintCode":null},"StockNo":"VS1179","RONo":"F3267226","IsCompleted":false,"PONo":null,"SalesPerson":{"Id":null},"Sales":{"PersonName":null},"Owner":{"Id":null,"Name":null,"Address":"...","Phone":null},"Location":{"Name":null},"ServiceRequest":{"Id":"4E513CBC-575C-EC11-8103-00155D9EC500","Number":"R-0007924240","LocalId":9959495},"Order":{"Id":null,"No":null},"Invoice":{"Id":null,"No":null},"Insurance":{"Id":null,"Name":null,"Address":null,"ContactInfo":""},"PolicyNumber":null,"ClaimNumber":null,"Deductible":null,"AccidentDate":null,"Inspection_Notes":"Contrato No \/ Rental Agreement: F3267226\r\nEconomico  \/ Stock: VS1179\r\nSeguro  \/ Coverage: LDW\r\nCD. Que Renta \/ Rental Location: SAN50\r\nCD. Recibe \/ Return Location: SAN50\r\nKM Salida \/ Mileage: 23701\r\nGas Salida \/ Fuel Tank Level: F\r\nDatos de contacto \/ Contact info: FAIRFIELD","EStatus":{"Id":5,"Name":"Draft"},"EStatusReason":{"Name":null},"CreateUTCTime":"2021-12-13T21:00:51.520","ModifyUTCTime":"2021-12-13T21:00:51.520","EstimationServices":null,"EstimationQuestions":null}
