{"EntityText":"#: E-000-2239570 Date: 12\/13\/2021 Stock: CA1255 RO: NPC82900 PO:  (2021 CHE CAVALILT LSGKB54H7MV117300) Client: BRUNO MONTIEL DE ?LA FUE","UTCTimestamp":"2022-03-28T04:26:09.920","InspectionId":"29D5BC29-389E-46D0-A774-67085410C6B4","InspectionNumber":"E-000-2239570","InspectionDate":"2021-12-13","InspectionType":{"Id":"04A19838-AEEC-4B12-BC41-77C52A166A0E","Name":"Hoja de Inspección - check in"},"Amount":0.00,"ApprovedAmount":0.00,"DiscountAmount":0.00000,"TaxAmount":0.00000,"FeesAmount":0.00000,"Employee":{"Id":"87A0AA24-1FCD-4E1F-AC82-8F8FEB5739DD","Name":"HERTZ TALLER PDC","ExternalID":null},"Client":{"Id":"3678F451-3C39-462F-9BD2-AB3AAA8537F7","Name":"BRUNO MONTIEL DE ?LA FUE","Address":"...","Phone":null,"ExternalID":null},"Vehicle":{"VIN":"LSGKB54H7MV117300","Year":2021,"Make":"CHE","Model":"CAVALILT","PlateNo":"YXU-706-D","Vehicle":{"Color":null},"Mileage":25907,"PaintCode":null},"StockNo":"CA1255","RONo":"NPC82900","IsCompleted":false,"PONo":null,"SalesPerson":{"Id":null},"Sales":{"PersonName":null},"Owner":{"Id":null,"Name":null,"Address":"...","Phone":null},"Location":{"Name":null},"ServiceRequest":{"Id":"367B19E0-475C-EC11-8103-00155D9EC500","Number":"R-0007923812","LocalId":9958724},"Order":{"Id":null,"No":null},"Invoice":{"Id":null,"No":null},"Insurance":{"Id":null,"Name":null,"Address":null,"ContactInfo":""},"PolicyNumber":null,"ClaimNumber":null,"Deductible":null,"AccidentDate":null,"Inspection_Notes":"Contrato No \/ Rental Agreement: NPC82900\r\nEconomico  \/ Stock: CA1255\r\nSeguro  \/ Coverage: \r\nCD. Que Renta \/ Rental Location: PDC60\r\nCD. Recibe \/ Return Location: PDC78\r\nKM Salida \/ Mileage: 25907\r\nGas Salida \/ Fuel Tank Level: 3\/4\r\nDatos de contacto \/ Contact info: ","EStatus":{"Id":5,"Name":"Draft"},"EStatusReason":{"Name":null},"CreateUTCTime":"2021-12-13T19:07:14.443","ModifyUTCTime":"2021-12-13T19:07:14.443","EstimationServices":null,"EstimationQuestions":null}
