{"EntityText":"#: E-000-2238426 Date: 12\/13\/2021 Stock: VS0267 RO: F3266539 PO:  (2020 VW VIRTUS 9BWDL5BZ5LP050783) Client: MARIZA","UTCTimestamp":"2022-03-28T04:23:37.427","InspectionId":"3C9AE03F-2DC5-481D-A6B2-444E723046C3","InspectionNumber":"E-000-2238426","InspectionDate":"2021-12-13","InspectionType":{"Id":"04A19838-AEEC-4B12-BC41-77C52A166A0E","Name":"Hoja de Inspección - check in"},"Amount":0.00,"ApprovedAmount":0.00,"DiscountAmount":0.00000,"TaxAmount":0.00000,"FeesAmount":0.00000,"Employee":{"Id":"D9181D69-A72F-4ED3-B334-455E1E58A55F","Name":"HERTZ F4KJL61QF193","ExternalID":null},"Client":{"Id":"AF7D0FDC-CB05-4BF0-AED7-AF8223EE3190","Name":"MARIZA","Address":"C JUAREZ","Phone":"160264","ExternalID":null},"Vehicle":{"VIN":"9BWDL5BZ5LP050783","Year":2020,"Make":"VW","Model":"VIRTUS","PlateNo":"YZE-686-C","Vehicle":{"Color":null},"Mileage":55465,"PaintCode":null},"StockNo":"VS0267","RONo":"F3266539","IsCompleted":false,"PONo":null,"SalesPerson":{"Id":null},"Sales":{"PersonName":null},"Owner":{"Id":null,"Name":null,"Address":"...","Phone":null},"Location":{"Name":null},"ServiceRequest":{"Id":"D73CE9EF-315C-EC11-8103-00155D9EC500","Number":"R-0007923240","LocalId":9957951},"Order":{"Id":null,"No":null},"Invoice":{"Id":null,"No":null},"Insurance":{"Id":null,"Name":null,"Address":null,"ContactInfo":""},"PolicyNumber":null,"ClaimNumber":null,"Deductible":null,"AccidentDate":null,"Inspection_Notes":"Contrato No \/ Rental Agreement: F3266539\r\nEconomico  \/ Stock: VS0267\r\nSeguro  \/ Coverage: CDW,CDW,TP,TP,PAI\r\nCD. Que Renta \/ Rental Location: TCAN52\r\nCD. Recibe \/ Return Location: TCAN52\r\nKM Salida \/ Mileage: 55465\r\nGas Salida \/ Fuel Tank Level: F\r\nDatos de contacto \/ Contact info: HTL MAYA DEL CARMEN","EStatus":{"Id":5,"Name":"Draft"},"EStatusReason":{"Name":null},"CreateUTCTime":"2021-12-13T16:30:15.980","ModifyUTCTime":"2021-12-13T16:30:15.980","EstimationServices":null,"EstimationQuestions":null}
