{"EntityText":"#: E-000-2240254 Date: 12\/13\/2021 Stock: NK1076 RO: F3267156 PO:  (2021 NSN KICKSADV 3N8CP5HE9ML484950) Client: CASANDRA","UTCTimestamp":"2022-03-28T04:27:26.117","InspectionId":"438B2218-A7EE-48A7-A262-63FB01D5E850","InspectionNumber":"E-000-2240254","InspectionDate":"2021-12-13","InspectionType":{"Id":"04A19838-AEEC-4B12-BC41-77C52A166A0E","Name":"Hoja de Inspección - check in"},"Amount":0.00,"ApprovedAmount":0.00,"DiscountAmount":0.00000,"TaxAmount":0.00000,"FeesAmount":0.00000,"Employee":{"Id":"897AF737-C484-4D9C-9FEA-C21B99EABE11","Name":"HERTZ SAN50-01","ExternalID":null},"Client":{"Id":"CD688BD3-6FBA-48AC-AB0E-3749532F5373","Name":"CASANDRA","Address":"20826 SHADY LN","Phone":"4795750876","ExternalID":null},"Vehicle":{"VIN":"3N8CP5HE9ML484950","Year":2021,"Make":"NSN","Model":"KICKSADV","PlateNo":"27-83-AVE","Vehicle":{"Color":null},"Mileage":12341,"PaintCode":null},"StockNo":"NK1076","RONo":"F3267156","IsCompleted":false,"PONo":null,"SalesPerson":{"Id":null},"Sales":{"PersonName":null},"Owner":{"Id":null,"Name":null,"Address":"...","Phone":null},"Location":{"Name":null},"ServiceRequest":{"Id":"3B1263DC-545C-EC11-8103-00155D9EC500","Number":"R-0007924154","LocalId":9959373},"Order":{"Id":null,"No":null},"Invoice":{"Id":null,"No":null},"Insurance":{"Id":null,"Name":null,"Address":null,"ContactInfo":""},"PolicyNumber":null,"ClaimNumber":null,"Deductible":null,"AccidentDate":null,"Inspection_Notes":"Contrato No \/ Rental Agreement: F3267156\r\nEconomico  \/ Stock: NK1076\r\nSeguro  \/ Coverage: CDW-2,RS ASSIST.,B2B,PAI,CDW2-LDW0%\r\nCD. Que Renta \/ Rental Location: SAN50\r\nCD. Recibe \/ Return Location: SAN50\r\nKM Salida \/ Mileage: 12341\r\nGas Salida \/ Fuel Tank Level: F\r\nDatos de contacto \/ Contact info: 5 DE FBRERO SJD","EStatus":{"Id":5,"Name":"Draft"},"EStatusReason":{"Name":null},"CreateUTCTime":"2021-12-13T20:40:16.160","ModifyUTCTime":"2021-12-13T20:40:16.160","EstimationServices":null,"EstimationQuestions":null}
