{"EntityText":"#: E-000-2242348 Date: 12\/13\/2021 Stock: NK1273 RO: F3267891 PO:  (2021 NSN KICKSADV 3N8CP5HE0ML517348) Client: CARLOS","UTCTimestamp":"2022-03-28T04:32:19.930","InspectionId":"50D94A99-AC96-40A3-99B1-8B20A8FC4599","InspectionNumber":"E-000-2242348","InspectionDate":"2021-12-13","InspectionType":{"Id":"04A19838-AEEC-4B12-BC41-77C52A166A0E","Name":"Hoja de Inspección - check in"},"Amount":0.00,"ApprovedAmount":0.00,"DiscountAmount":0.00000,"TaxAmount":0.00000,"FeesAmount":0.00000,"Employee":{"Id":"897AF737-C484-4D9C-9FEA-C21B99EABE11","Name":"HERTZ SAN50-01","ExternalID":null},"Client":{"Id":"9D576058-CC6E-46E0-BB5A-3A29CB6C554B","Name":"CARLOS","Address":"CENTRO","Phone":"525566308476","ExternalID":null},"Vehicle":{"VIN":"3N8CP5HE0ML517348","Year":2021,"Make":"NSN","Model":"KICKSADV","PlateNo":"34-73-AVE","Vehicle":{"Color":null},"Mileage":23869,"PaintCode":null},"StockNo":"NK1273","RONo":"F3267891","IsCompleted":false,"PONo":null,"SalesPerson":{"Id":null},"Sales":{"PersonName":null},"Owner":{"Id":null,"Name":null,"Address":"...","Phone":null},"Location":{"Name":null},"ServiceRequest":{"Id":"5E379E4E-995C-EC11-8103-00155D9EC500","Number":"R-0007925201","LocalId":9960936},"Order":{"Id":null,"No":null},"Invoice":{"Id":null,"No":null},"Insurance":{"Id":null,"Name":null,"Address":null,"ContactInfo":""},"PolicyNumber":null,"ClaimNumber":null,"Deductible":null,"AccidentDate":null,"Inspection_Notes":"Contrato No \/ Rental Agreement: F3267891\r\nEconomico  \/ Stock: NK1273\r\nSeguro  \/ Coverage: LDW,B2B\r\nCD. Que Renta \/ Rental Location: SAN50\r\nCD. Recibe \/ Return Location: SAN50\r\nKM Salida \/ Mileage: 23869\r\nGas Salida \/ Fuel Tank Level: 5\/8\r\nDatos de contacto \/ Contact info: HARDROCK","EStatus":{"Id":5,"Name":"Draft"},"EStatusReason":{"Name":null},"CreateUTCTime":"2021-12-14T04:50:12.410","ModifyUTCTime":"2021-12-14T04:50:12.410","EstimationServices":null,"EstimationQuestions":null}
