{"EntityText":"#: E-000-2237250 Date: 12\/13\/2021 Stock: ML2014 RO: F3266099 PO:  (2022 MTSH L200 D MMBNLV566NH009070) Client: ALEXANDER","UTCTimestamp":"2022-03-28T04:20:51.597","InspectionId":"536A186C-8A55-4C56-A507-87F9241298B9","InspectionNumber":"E-000-2237250","InspectionDate":"2021-12-13","InspectionType":{"Id":"04A19838-AEEC-4B12-BC41-77C52A166A0E","Name":"Hoja de Inspección - check in"},"Amount":0.00,"ApprovedAmount":0.00,"DiscountAmount":0.00000,"TaxAmount":0.00000,"FeesAmount":0.00000,"Employee":{"Id":"D9181D69-A72F-4ED3-B334-455E1E58A55F","Name":"HERTZ F4KJL61QF193","ExternalID":null},"Client":{"Id":"5F83EAC8-EACA-49F7-A7E6-3F651B25B7F6","Name":"ALEXANDER","Address":"PENALIZACION","Phone":"9981234567","ExternalID":null},"Vehicle":{"VIN":"MMBNLV566NH009070","Year":2022,"Make":"MTSH","Model":"L200 D","PlateNo":"5-SWF-86A","Vehicle":{"Color":null},"Mileage":13023,"PaintCode":null},"StockNo":"ML2014","RONo":"F3266099","IsCompleted":false,"PONo":null,"SalesPerson":{"Id":null},"Sales":{"PersonName":null},"Owner":{"Id":null,"Name":null,"Address":"...","Phone":null},"Location":{"Name":null},"ServiceRequest":{"Id":"E469DAC3-EC5B-EC11-8103-00155D9EC500","Number":"R-0007922652","LocalId":9956702},"Order":{"Id":null,"No":null},"Invoice":{"Id":null,"No":null},"Insurance":{"Id":null,"Name":null,"Address":null,"ContactInfo":""},"PolicyNumber":null,"ClaimNumber":null,"Deductible":null,"AccidentDate":null,"Inspection_Notes":"Contrato No \/ Rental Agreement: F3266099\r\nEconomico  \/ Stock: ML2014\r\nSeguro  \/ Coverage: \r\nCD. Que Renta \/ Rental Location: FCAN50\r\nCD. Recibe \/ Return Location: FCAN50\r\nKM Salida \/ Mileage: 13023\r\nGas Salida \/ Fuel Tank Level: F\r\nDatos de contacto \/ Contact info: PENALIZACION","EStatus":{"Id":5,"Name":"Draft"},"EStatusReason":{"Name":null},"CreateUTCTime":"2021-12-13T08:15:06.447","ModifyUTCTime":"2021-12-13T08:15:06.447","EstimationServices":null,"EstimationQuestions":null}
