{"EntityText":"#: E-000-2240318 Date: 12\/13\/2021 Stock: KR1039 RO: F3267182 PO:  (2021 KIA RIO 3KPA24BC7ME417982) Client: JORGE","UTCTimestamp":"2022-03-28T04:28:03.503","InspectionId":"5423AD76-732C-407E-92B5-322BFE36C68E","InspectionNumber":"E-000-2240318","InspectionDate":"2021-12-13","InspectionType":{"Id":"04A19838-AEEC-4B12-BC41-77C52A166A0E","Name":"Hoja de Inspección - check in"},"Amount":0.00,"ApprovedAmount":0.00,"DiscountAmount":0.00000,"TaxAmount":0.00000,"FeesAmount":0.00000,"Employee":{"Id":"897AF737-C484-4D9C-9FEA-C21B99EABE11","Name":"HERTZ SAN50-01","ExternalID":null},"Client":{"Id":"0C74A1BC-BB07-40E3-9FF1-1EA7B27D1A93","Name":"JORGE","Address":"C QUERETARO 253","Phone":"6462411031","ExternalID":null},"Vehicle":{"VIN":"3KPA24BC7ME417982","Year":2021,"Make":"KIA","Model":"RIO","PlateNo":"20-85-AVE","Vehicle":{"Color":null},"Mileage":11244,"PaintCode":null},"StockNo":"KR1039","RONo":"F3267182","IsCompleted":false,"PONo":null,"SalesPerson":{"Id":null},"Sales":{"PersonName":null},"Owner":{"Id":null,"Name":null,"Address":"...","Phone":null},"Location":{"Name":null},"ServiceRequest":{"Id":"15F2E391-555C-EC11-8103-00155D9EC500","Number":"R-0007924186","LocalId":9959410},"Order":{"Id":null,"No":null},"Invoice":{"Id":null,"No":null},"Insurance":{"Id":null,"Name":null,"Address":null,"ContactInfo":""},"PolicyNumber":null,"ClaimNumber":null,"Deductible":null,"AccidentDate":null,"Inspection_Notes":"Contrato No \/ Rental Agreement: F3267182\r\nEconomico  \/ Stock: KR1039\r\nSeguro  \/ Coverage: LDW,B2B,ALI\r\nCD. Que Renta \/ Rental Location: SAN50\r\nCD. Recibe \/ Return Location: SAN50\r\nKM Salida \/ Mileage: 11244\r\nGas Salida \/ Fuel Tank Level: F\r\nDatos de contacto \/ Contact info: CITY EXPRESS","EStatus":{"Id":5,"Name":"Draft"},"EStatusReason":{"Name":null},"CreateUTCTime":"2021-12-13T20:45:20.280","ModifyUTCTime":"2021-12-13T20:45:20.280","EstimationServices":null,"EstimationQuestions":null}
