{"EntityText":"#: E-000-2240319 Date: 12\/13\/2021 Stock: AU1155 RO: F3267183 PO:  (2021 CHE AVEOLS LSGHD52H1MD078443) Client: J CARMEN","UTCTimestamp":"2022-03-28T04:28:03.503","InspectionId":"54A81457-BC29-4F33-BAF4-8B8E3E0CBCF3","InspectionNumber":"E-000-2240319","InspectionDate":"2021-12-13","InspectionType":{"Id":"33034816-D00A-49F6-8AA5-55D54FDE8907","Name":"Hoja de Inspeccion - check out"},"Amount":0.00,"ApprovedAmount":0.00,"DiscountAmount":0.00000,"TaxAmount":0.00000,"FeesAmount":0.00000,"Employee":{"Id":"7272EF35-BA42-4012-A525-ECB34FF20C5B","Name":"HERTZ R52M10TDL7W","ExternalID":null},"Client":{"Id":"0CDEFAE0-09FE-4448-9A98-2A3A9678E853","Name":"J CARMEN","Address":"DR EULOGIO RUIZ","Phone":"7292722199","ExternalID":null},"Vehicle":{"VIN":"LSGHD52H1MD078443","Year":2021,"Make":"CHE","Model":"AVEOLS","PlateNo":"EPA-70-90","Vehicle":{"Color":null},"Mileage":27452,"PaintCode":null},"StockNo":"AU1155","RONo":"F3267183","IsCompleted":false,"PONo":null,"SalesPerson":{"Id":null},"Sales":{"PersonName":null},"Owner":{"Id":null,"Name":null,"Address":"...","Phone":null},"Location":{"Name":null},"ServiceRequest":{"Id":"18F2E391-555C-EC11-8103-00155D9EC500","Number":"R-0007924187","LocalId":9959411},"Order":{"Id":null,"No":null},"Invoice":{"Id":null,"No":null},"Insurance":{"Id":null,"Name":null,"Address":null,"ContactInfo":""},"PolicyNumber":null,"ClaimNumber":null,"Deductible":null,"AccidentDate":null,"Inspection_Notes":"Contrato No \/ Rental Agreement: F3267183\r\nEconomico  \/ Stock: AU1155\r\nSeguro  \/ Coverage: CDW-2\r\nCD. Que Renta \/ Rental Location: MTY50\r\nCD. Recibe \/ Return Location: MTY53\r\nKM Salida \/ Mileage: 27452\r\nGas Salida \/ Fuel Tank Level: F\r\nDatos de contacto \/ Contact info: HO?LIDAHY IN FUNDIDORA","EStatus":{"Id":5,"Name":"Draft"},"EStatusReason":{"Name":null},"CreateUTCTime":"2021-12-13T20:45:22.593","ModifyUTCTime":"2021-12-13T20:45:22.593","EstimationServices":null,"EstimationQuestions":null}
