{"EntityText":"#: E-000-2239925 Date: 12\/13\/2021 Stock: AU1007 RO: F3267057 PO:  (2021 CHE AVEOLS LSGHD52H5MD025972) Client: BERTHA INEZ","UTCTimestamp":"2022-03-28T04:26:50.300","InspectionId":"7482ECF5-AFE8-4B51-A4EC-8025B2BD0B89","InspectionNumber":"E-000-2239925","InspectionDate":"2021-12-13","InspectionType":{"Id":"33034816-D00A-49F6-8AA5-55D54FDE8907","Name":"Hoja de Inspeccion - check out"},"Amount":0.00,"ApprovedAmount":0.00,"DiscountAmount":0.00000,"TaxAmount":0.00000,"FeesAmount":0.00000,"Employee":{"Id":"897AF737-C484-4D9C-9FEA-C21B99EABE11","Name":"HERTZ SAN50-01","ExternalID":null},"Client":{"Id":"67CBFF3A-CCE0-4696-81E7-7F066C1C539D","Name":"BERTHA INEZ","Address":"C GUAYABO MZA 6 LTE 23","Phone":"9621291674","ExternalID":null},"Vehicle":{"VIN":"LSGHD52H5MD025972","Year":2021,"Make":"CHE","Model":"AVEOLS","PlateNo":"11-41-AVE","Vehicle":{"Color":null},"Mileage":24494,"PaintCode":null},"StockNo":"AU1007","RONo":"F3267057","IsCompleted":false,"PONo":null,"SalesPerson":{"Id":null},"Sales":{"PersonName":null},"Owner":{"Id":null,"Name":null,"Address":"...","Phone":null},"Location":{"Name":null},"ServiceRequest":{"Id":"995553E2-4D5C-EC11-8103-00155D9EC500","Number":"R-0007923990","LocalId":9959127},"Order":{"Id":null,"No":null},"Invoice":{"Id":null,"No":null},"Insurance":{"Id":null,"Name":null,"Address":null,"ContactInfo":""},"PolicyNumber":null,"ClaimNumber":null,"Deductible":null,"AccidentDate":null,"Inspection_Notes":"Contrato No \/ Rental Agreement: F3267057\r\nEconomico  \/ Stock: AU1007\r\nSeguro  \/ Coverage: LDW\r\nCD. Que Renta \/ Rental Location: SAN50\r\nCD. Recibe \/ Return Location: SAN50\r\nKM Salida \/ Mileage: 24494\r\nGas Salida \/ Fuel Tank Level: 7\/8\r\nDatos de contacto \/ Contact info: HOTEL ROYAL SOLARIS","EStatus":{"Id":5,"Name":"Draft"},"EStatusReason":{"Name":null},"CreateUTCTime":"2021-12-13T19:50:22.643","ModifyUTCTime":"2021-12-13T19:50:22.643","EstimationServices":null,"EstimationQuestions":null}
