{"EntityText":"#: E-000-2242008 Date: 12\/13\/2021 Stock: CA1178 RO: F3267773 PO:  (2021 CHE CAVALILT LSGKB54H8MV096604) Client: MALIA NANI","UTCTimestamp":"2022-03-28T04:31:47.343","InspectionId":"7A1233FB-444F-44C6-9B68-DEC5541D85CC","InspectionNumber":"E-000-2242008","InspectionDate":"2021-12-13","InspectionType":{"Id":"04A19838-AEEC-4B12-BC41-77C52A166A0E","Name":"Hoja de Inspección - check in"},"Amount":0.00,"ApprovedAmount":0.00,"DiscountAmount":0.00000,"TaxAmount":0.00000,"FeesAmount":0.00000,"Employee":{"Id":"D9181D69-A72F-4ED3-B334-455E1E58A55F","Name":"HERTZ F4KJL61QF193","ExternalID":null},"Client":{"Id":"E1A12005-BEDA-47E4-A14D-E42E6B3A1DB7","Name":"MALIA NANI","Address":"196 S CATALINA ST","Phone":"4156665619","ExternalID":null},"Vehicle":{"VIN":"LSGKB54H8MV096604","Year":2021,"Make":"CHE","Model":"CAVALILT","PlateNo":"ZBT-504-C","Vehicle":{"Color":null},"Mileage":22046,"PaintCode":null},"StockNo":"CA1178","RONo":"F3267773","IsCompleted":false,"PONo":null,"SalesPerson":{"Id":null},"Sales":{"PersonName":null},"Owner":{"Id":null,"Name":null,"Address":"...","Phone":null},"Location":{"Name":null},"ServiceRequest":{"Id":"7E8380F3-825C-EC11-8103-00155D9EC500","Number":"R-0007925031","LocalId":9960701},"Order":{"Id":null,"No":null},"Invoice":{"Id":null,"No":null},"Insurance":{"Id":null,"Name":null,"Address":null,"ContactInfo":""},"PolicyNumber":null,"ClaimNumber":null,"Deductible":null,"AccidentDate":null,"Inspection_Notes":"Contrato No \/ Rental Agreement: F3267773\r\nEconomico  \/ Stock: CA1178\r\nSeguro  \/ Coverage: CDW\r\nCD. Que Renta \/ Rental Location: TCAN52\r\nCD. Recibe \/ Return Location: TCAN52\r\nKM Salida \/ Mileage: 22046\r\nGas Salida \/ Fuel Tank Level: F\r\nDatos de contacto \/ Contact info: PUERTO AVENTURAS","EStatus":{"Id":5,"Name":"Draft"},"EStatusReason":{"Name":null},"CreateUTCTime":"2021-12-14T02:10:09.773","ModifyUTCTime":"2021-12-14T02:10:09.773","EstimationServices":null,"EstimationQuestions":null}
