{"EntityText":"#: E-000-2241934 Date: 12\/13\/2021 Stock: NM0254 RO: F3267747 PO:  (2020 NSN MARCHABS 3N1CK3CD0LL207408) Client: DIDIER DE JESUS","UTCTimestamp":"2022-03-28T04:31:47.343","InspectionId":"7EC29E1C-6045-4E90-82C7-F95D4B0465C4","InspectionNumber":"E-000-2241934","InspectionDate":"2021-12-13","InspectionType":{"Id":"04A19838-AEEC-4B12-BC41-77C52A166A0E","Name":"Hoja de Inspección - check in"},"Amount":0.00,"ApprovedAmount":0.00,"DiscountAmount":0.00000,"TaxAmount":0.00000,"FeesAmount":0.00000,"Employee":{"Id":"D9181D69-A72F-4ED3-B334-455E1E58A55F","Name":"HERTZ F4KJL61QF193","ExternalID":null},"Client":{"Id":"4C3939EB-E7BA-4F79-9E22-71BEEA167993","Name":"DIDIER DE JESUS","Address":"BLVD 15 DE MAYO 4732","Phone":"2213492182","ExternalID":null},"Vehicle":{"VIN":"3N1CK3CD0LL207408","Year":2020,"Make":"NSN","Model":"MARCHABS","PlateNo":"YYB-731-C","Vehicle":{"Color":null},"Mileage":53435,"PaintCode":null},"StockNo":"NM0254","RONo":"F3267747","IsCompleted":false,"PONo":null,"SalesPerson":{"Id":null},"Sales":{"PersonName":null},"Owner":{"Id":null,"Name":null,"Address":"...","Phone":null},"Location":{"Name":null},"ServiceRequest":{"Id":"B00C6625-805C-EC11-8103-00155D9EC500","Number":"R-0007924994","LocalId":9960659},"Order":{"Id":null,"No":null},"Invoice":{"Id":null,"No":null},"Insurance":{"Id":null,"Name":null,"Address":null,"ContactInfo":""},"PolicyNumber":null,"ClaimNumber":null,"Deductible":null,"AccidentDate":null,"Inspection_Notes":"Contrato No \/ Rental Agreement: F3267747\r\nEconomico  \/ Stock: NM0254\r\nSeguro  \/ Coverage: CDW\r\nCD. Que Renta \/ Rental Location: TCAN52\r\nCD. Recibe \/ Return Location: TCAN52\r\nKM Salida \/ Mileage: 53435\r\nGas Salida \/ Fuel Tank Level: F\r\nDatos de contacto \/ Contact info: RDCIAL LAS AMERICAS CUN","EStatus":{"Id":5,"Name":"Draft"},"EStatusReason":{"Name":null},"CreateUTCTime":"2021-12-14T01:50:09.450","ModifyUTCTime":"2021-12-14T01:50:09.450","EstimationServices":null,"EstimationQuestions":null}
