{"EntityText":"#: E-000-2239524 Date: 12\/13\/2021 Stock: MC2045 RO: F3266905 PO:  (2022 MINI SCLASSIC WMW51DK04N2P82836) Client: RAMON","UTCTimestamp":"2022-03-28T04:26:09.920","InspectionId":"818D1B2C-E846-4005-8C8B-2C85DFF7AB79","InspectionNumber":"E-000-2239524","InspectionDate":"2021-12-13","InspectionType":{"Id":"04A19838-AEEC-4B12-BC41-77C52A166A0E","Name":"Hoja de Inspección - check in"},"Amount":0.00,"ApprovedAmount":0.00,"DiscountAmount":0.00000,"TaxAmount":0.00000,"FeesAmount":0.00000,"Employee":{"Id":"4C1D4F7F-6DC2-4CCB-B1C9-068DC167B80B","Name":"HERTZ GDL50","ExternalID":null},"Client":{"Id":"843F503B-E0DC-4949-9653-390BFE9D4376","Name":"RAMON","Address":"PARQUE NOROESTE","Phone":"6681144916","ExternalID":null},"Vehicle":{"VIN":"WMW51DK04N2P82836","Year":2022,"Make":"MINI","Model":"SCLASSIC","PlateNo":"DAC-82-87","Vehicle":{"Color":null},"Mileage":11019,"PaintCode":null},"StockNo":"MC2045","RONo":"F3266905","IsCompleted":false,"PONo":null,"SalesPerson":{"Id":null},"Sales":{"PersonName":null},"Owner":{"Id":null,"Name":null,"Address":"...","Phone":null},"Location":{"Name":null},"ServiceRequest":{"Id":"E574F63C-475C-EC11-8103-00155D9EC500","Number":"R-0007923789","LocalId":9958695},"Order":{"Id":null,"No":null},"Invoice":{"Id":null,"No":null},"Insurance":{"Id":null,"Name":null,"Address":null,"ContactInfo":""},"PolicyNumber":null,"ClaimNumber":null,"Deductible":null,"AccidentDate":null,"Inspection_Notes":"Contrato No \/ Rental Agreement: F3266905\r\nEconomico  \/ Stock: MC2045\r\nSeguro  \/ Coverage: CDW-2,CDW2 - CDW,ALI,PAI,RS ASSIST.\r\nCD. Que Renta \/ Rental Location: DGUA51\r\nCD. Recibe \/ Return Location: DGUA51\r\nKM Salida \/ Mileage: 11019\r\nGas Salida \/ Fuel Tank Level: F\r\nDatos de contacto \/ Contact info: PILAR SUAREZ","EStatus":{"Id":5,"Name":"Draft"},"EStatusReason":{"Name":null},"CreateUTCTime":"2021-12-13T19:02:41.357","ModifyUTCTime":"2021-12-13T19:02:41.357","EstimationServices":null,"EstimationQuestions":null}
