{"EntityText":"#: E-000-2238956 Date: 12\/13\/2021 Stock: JG0013 RO: NCN37880 PO:  (2020 JEEP GLADIATO 1C6HJTFG1LL186180) Client: VICTOR MANUE CORTES TORRES","UTCTimestamp":"2022-03-28T04:24:53.330","InspectionId":"87B4C602-210C-41EB-AC94-4B7676EE02C4","InspectionNumber":"E-000-2238956","InspectionDate":"2021-12-13","InspectionType":{"Id":"04A19838-AEEC-4B12-BC41-77C52A166A0E","Name":"Hoja de Inspección - check in"},"Amount":0.00,"ApprovedAmount":0.00,"DiscountAmount":0.00000,"TaxAmount":0.00000,"FeesAmount":0.00000,"Employee":{"Id":"2D314522-21CE-491E-9E0F-2413899B2FE9","Name":"HERTZ CAN51","ExternalID":null},"Client":{"Id":"B56D4746-CF2B-4F44-BEC5-34BC9C6C321D","Name":"VICTOR MANUE CORTES TORRES","Address":"...","Phone":null,"ExternalID":null},"Vehicle":{"VIN":"1C6HJTFG1LL186180","Year":2020,"Make":"JEEP","Model":"GLADIATO","PlateNo":"YR-7820-C","Vehicle":{"Color":null},"Mileage":45756,"PaintCode":null},"StockNo":"JG0013","RONo":"NCN37880","IsCompleted":false,"PONo":null,"SalesPerson":{"Id":null},"Sales":{"PersonName":null},"Owner":{"Id":null,"Name":null,"Address":"...","Phone":null},"Location":{"Name":null},"ServiceRequest":{"Id":"FBC11406-3B5C-EC11-8103-00155D9EC500","Number":"R-0007923505","LocalId":9958307},"Order":{"Id":null,"No":null},"Invoice":{"Id":null,"No":null},"Insurance":{"Id":null,"Name":null,"Address":null,"ContactInfo":""},"PolicyNumber":null,"ClaimNumber":null,"Deductible":null,"AccidentDate":null,"Inspection_Notes":"Contrato No \/ Rental Agreement: NCN37880\r\nEconomico  \/ Stock: JG0013\r\nSeguro  \/ Coverage: \r\nCD. Que Renta \/ Rental Location: CAN50\r\nCD. Recibe \/ Return Location: CAN51\r\nKM Salida \/ Mileage: 45756\r\nGas Salida \/ Fuel Tank Level: F\r\nDatos de contacto \/ Contact info: ","EStatus":{"Id":5,"Name":"Draft"},"EStatusReason":{"Name":null},"CreateUTCTime":"2021-12-13T17:35:21.227","ModifyUTCTime":"2021-12-13T17:35:21.227","EstimationServices":null,"EstimationQuestions":null}
