{"EntityText":"#: E-000-1732666 Date: 12\/13\/2021 Stock: CR1002 RO: F3091028 PO:  (2021 VW T-CROSS 9BWBL6BF1M4020976) Client: VICENTE FEDERICO","UTCTimestamp":"2022-03-28T04:19:39.813","InspectionId":"C0A5F343-9540-4572-B79E-F0BC3A07C2EC","InspectionNumber":"E-000-1732666","InspectionDate":"2021-12-13","InspectionType":{"Id":"04A19838-AEEC-4B12-BC41-77C52A166A0E","Name":"Hoja de Inspección - check in"},"Amount":0.00,"ApprovedAmount":0.00,"DiscountAmount":0.00000,"TaxAmount":0.00000,"FeesAmount":0.00000,"Employee":{"Id":"D43C5968-7DBA-4003-A590-1957E72842E4","Name":"HERTZ PDC61","ExternalID":null},"Client":{"Id":"2316C432-E26C-42AA-B287-C382B35F31D1","Name":"VICENTE FEDERICO","Address":"CDA DEL IMAN MZA 4","Phone":"5539005239","ExternalID":null},"Vehicle":{"VIN":"9BWBL6BF1M4020976","Year":2021,"Make":"VW","Model":"T-CROSS","PlateNo":"YXZ-997-D","Vehicle":{"Color":null},"Mileage":9010,"PaintCode":null},"StockNo":"CR1002","RONo":"F3091028","IsCompleted":false,"PONo":null,"SalesPerson":{"Id":null},"Sales":{"PersonName":null},"Owner":{"Id":null,"Name":null,"Address":"...","Phone":null},"Location":{"Name":null},"ServiceRequest":{"Id":"CDA6BECA-EE04-EC11-80FE-00155D9EC500","Number":"R-0007670309","LocalId":9530204},"Order":{"Id":null,"No":null},"Invoice":{"Id":null,"No":null},"Insurance":{"Id":null,"Name":null,"Address":null,"ContactInfo":""},"PolicyNumber":null,"ClaimNumber":null,"Deductible":null,"AccidentDate":null,"Inspection_Notes":"Contrato No \/ Rental Agreement: F3091028\r\nEconomico  \/ Stock: CR1002\r\nSeguro  \/ Coverage: LDW,PAI,ALI,RS ASSIST.,B2B\r\nCD. Que Renta \/ Rental Location: CAN50\r\nCD. Recibe \/ Return Location: CAN50\r\nKM Salida \/ Mileage: 9010\r\nGas Salida \/ Fuel Tank Level: F\r\nDatos de contacto \/ Contact info: MARRIOT CANCUN HTL","EStatus":{"Id":5,"Name":"Draft"},"EStatusReason":{"Name":null},"CreateUTCTime":"2021-08-24T15:20:20.200","ModifyUTCTime":"2021-08-24T15:20:20.200","EstimationServices":null,"EstimationQuestions":null}
