{"EntityText":"#: E-000-1792416 Date: 12\/13\/2021 Stock: NM0326 RO: NHU96272 PO:  (2020 NSN MARCHABS 3N1CK3CD4LL212191) Client: JAIME","UTCTimestamp":"2022-03-28T04:19:39.813","InspectionId":"ED6D3B7A-157D-4B4A-A402-F0D6CDF6C664","InspectionNumber":"E-000-1792416","InspectionDate":"2021-12-13","InspectionType":{"Id":"04A19838-AEEC-4B12-BC41-77C52A166A0E","Name":"Hoja de Inspección - check in"},"Amount":0.00,"ApprovedAmount":0.00,"DiscountAmount":0.00000,"TaxAmount":0.00000,"FeesAmount":0.00000,"Employee":{"Id":"D43C5968-7DBA-4003-A590-1957E72842E4","Name":"HERTZ PDC61","ExternalID":null},"Client":{"Id":"AB261007-F785-489C-AA5D-43EED38976AE","Name":"JAIME","Address":"1","Phone":null,"ExternalID":null},"Vehicle":{"VIN":"3N1CK3CD4LL212191","Year":2020,"Make":"NSN","Model":"MARCHABS","PlateNo":"YZF-162-C","Vehicle":{"Color":null},"Mileage":49417,"PaintCode":null},"StockNo":"NM0326","RONo":"NHU96272","IsCompleted":false,"PONo":null,"SalesPerson":{"Id":null},"Sales":{"PersonName":null},"Owner":{"Id":null,"Name":null,"Address":"...","Phone":null},"Location":{"Name":null},"ServiceRequest":{"Id":"58DD36A1-0910-EC11-80FE-00155D9EC500","Number":"R-0007700199","LocalId":9581615},"Order":{"Id":null,"No":null},"Invoice":{"Id":null,"No":null},"Insurance":{"Id":null,"Name":null,"Address":null,"ContactInfo":""},"PolicyNumber":null,"ClaimNumber":null,"Deductible":null,"AccidentDate":null,"Inspection_Notes":"Contrato No \/ Rental Agreement: NHU96272\r\nEconomico  \/ Stock: NM0326\r\nSeguro  \/ Coverage: \r\nCD. Que Renta \/ Rental Location: TUL60\r\nCD. Recibe \/ Return Location: TUL60\r\nKM Salida \/ Mileage: 49417\r\nGas Salida \/ Fuel Tank Level: 3\/4\r\nDatos de contacto \/ Contact info: ","EStatus":{"Id":5,"Name":"Draft"},"EStatusReason":{"Name":null},"CreateUTCTime":"2021-09-07T18:30:13.430","ModifyUTCTime":"2021-09-07T18:30:13.430","EstimationServices":null,"EstimationQuestions":null}
