{"EntityText":"#: E-000-2238187 Date: 12\/13\/2021 Stock: X21022 RO: F3266459 PO:  (2021 NSN XTRAIL2R JN8BT27TXMW126613) Client: OSCAR","UTCTimestamp":"2022-03-28T04:22:56.547","InspectionId":"FD4F36A2-4CEF-451D-840A-BE39FBF94AB4","InspectionNumber":"E-000-2238187","InspectionDate":"2021-12-13","InspectionType":{"Id":"33034816-D00A-49F6-8AA5-55D54FDE8907","Name":"Hoja de Inspeccion - check out"},"Amount":0.00,"ApprovedAmount":0.00,"DiscountAmount":0.00000,"TaxAmount":0.00000,"FeesAmount":0.00000,"Employee":{"Id":"7BE88A58-AC8D-4353-9D09-1A43717537A5","Name":"HERTZ CUU50","ExternalID":null},"Client":{"Id":"F995DF90-395F-44C4-B1BE-A90B19B920EE","Name":"OSCAR","Address":"PEÑA BLANCA","Phone":"5555706468","ExternalID":null},"Vehicle":{"VIN":"JN8BT27TXMW126613","Year":2021,"Make":"NSN","Model":"XTRAIL2R","PlateNo":"EPA-64-64","Vehicle":{"Color":null},"Mileage":43172,"PaintCode":null},"StockNo":"X21022","RONo":"F3266459","IsCompleted":false,"PONo":null,"SalesPerson":{"Id":null},"Sales":{"PersonName":null},"Owner":{"Id":null,"Name":null,"Address":"...","Phone":null},"Location":{"Name":null},"ServiceRequest":{"Id":"0E17BB12-2D5C-EC11-8103-00155D9EC500","Number":"R-0007923121","LocalId":9957744},"Order":{"Id":null,"No":null},"Invoice":{"Id":null,"No":null},"Insurance":{"Id":null,"Name":null,"Address":null,"ContactInfo":""},"PolicyNumber":null,"ClaimNumber":null,"Deductible":null,"AccidentDate":null,"Inspection_Notes":"Contrato No \/ Rental Agreement: F3266459\r\nEconomico  \/ Stock: X21022\r\nSeguro  \/ Coverage: LDW,B2B,RS ASSIST.\r\nCD. Que Renta \/ Rental Location: CUU50\r\nCD. Recibe \/ Return Location: CUU50\r\nKM Salida \/ Mileage: 43172\r\nGas Salida \/ Fuel Tank Level: F\r\nDatos de contacto \/ Contact info: OFICINA","EStatus":{"Id":5,"Name":"Draft"},"EStatusReason":{"Name":null},"CreateUTCTime":"2021-12-13T15:55:29.103","ModifyUTCTime":"2021-12-13T15:55:29.103","EstimationServices":null,"EstimationQuestions":null}
