{"EntityText":"#: E-000-1684602 Date: 12\/13\/2021 Stock: SU0031 RO: VIL77648 PO:  (2020 CHE SUBRBANB 1GNSC8KC8LR136924) Client: SERAFIN IGNACIO","UTCTimestamp":"2022-03-28T04:19:39.813","InspectionId":"FE664CDF-614E-4673-8524-929E0F2DE313","InspectionNumber":"E-000-1684602","InspectionDate":"2021-12-13","InspectionType":{"Id":"04A19838-AEEC-4B12-BC41-77C52A166A0E","Name":"Hoja de Inspección - check in"},"Amount":0.00,"ApprovedAmount":0.00,"DiscountAmount":0.00000,"TaxAmount":0.00000,"FeesAmount":0.00000,"Employee":{"Id":"C33CCB26-FE72-4F9B-BCCF-D8DEACBE1013","Name":"HERTZ R52M40KZAXT","ExternalID":null},"Client":{"Id":"98DBAE81-A319-4044-A141-33CEC2F22084","Name":"SERAFIN IGNACIO","Address":"...","Phone":null,"ExternalID":null},"Vehicle":{"VIN":"1GNSC8KC8LR136924","Year":2020,"Make":"CHE","Model":"SUBRBANB","PlateNo":"YZF-712-C","Vehicle":{"Color":null},"Mileage":32798,"PaintCode":null},"StockNo":"SU0031","RONo":"VIL77648","IsCompleted":false,"PONo":null,"SalesPerson":{"Id":null},"Sales":{"PersonName":null},"Owner":{"Id":null,"Name":null,"Address":"...","Phone":null},"Location":{"Name":null},"ServiceRequest":{"Id":"98665D66-B9FB-EB11-80FE-00155D9EC500","Number":"R-0007646254","LocalId":9486610},"Order":{"Id":null,"No":null},"Invoice":{"Id":null,"No":null},"Insurance":{"Id":null,"Name":null,"Address":null,"ContactInfo":""},"PolicyNumber":null,"ClaimNumber":null,"Deductible":null,"AccidentDate":null,"Inspection_Notes":"Contrato No \/ Rental Agreement: VIL77648\r\nEconomico  \/ Stock: SU0031\r\nSeguro  \/ Coverage: \r\nCD. Que Renta \/ Rental Location: VIL62\r\nCD. Recibe \/ Return Location: VIL50\r\nKM Salida \/ Mileage: 32798\r\nGas Salida \/ Fuel Tank Level: F\r\nDatos de contacto \/ Contact info: ","EStatus":{"Id":5,"Name":"Draft"},"EStatusReason":{"Name":null},"CreateUTCTime":"2021-08-12T22:05:30.577","ModifyUTCTime":"2021-08-12T22:05:30.577","EstimationServices":null,"EstimationQuestions":null}
